tests/test_builder_async.py
tests/test_builder_sync.py
tests/test_stream_async.py
tests/test_stream_sync.py
zipgen/__init__.py
zipgen/__main__.py
zipgen/build.py
zipgen/compress.py
zipgen/constant.py
zipgen/convert.py
zipgen/pack.py
zipgen/stream.py
zipgen-0.1.6.dist-info/LICENCE
zipgen-0.1.6.dist-info/METADATA
zipgen-0.1.6.dist-info/WHEEL
zipgen-0.1.6.dist-info/top_level.txt
zipgen-0.1.6.dist-info/RECORD
