Metadata-Version: 2.1
Name: zipgen
Version: 0.1.6
Summary: A zip file generator.
Author-email: 33TU <eetu.programmer@gmail.com>
Project-URL: Homepage, https://github.com/33TU/zipgen
Classifier: Programming Language :: Python :: 3.7
Classifier: Programming Language :: Python :: 3.8
Classifier: Programming Language :: Python :: 3.9
Classifier: Programming Language :: Python :: 3.10
Classifier: Programming Language :: Python :: 3.11
Classifier: Programming Language :: Python :: Implementation :: PyPy
Classifier: License :: OSI Approved :: MIT License
Classifier: Operating System :: OS Independent
Requires-Python: >=3.7
License-File: LICENCE
Requires-Dist: typing-extensions ; python_version < "3.8"
